pygsfit/__init__.py
pygsfit/fitting_result_restore.py
pygsfit/pygsfit.py
pygsfit/binaries/GRFF_DEM_Transfer.so
pygsfit/binaries/GRFF_DEM_Transfer_64.dll
pygsfit/binaries/GRFF_DEM_Transfer_mac_arm64.so
pygsfit/binaries/MWTransferArr.so
pygsfit/binaries/MWTransferArr64.dll
pygsfit/binaries/MWTransferArr_arm64.so
pygsfit/binaries/MWTransferArr_compiled.cpython-310-darwin.so
pygsfit/binaries/fit_Spectrum_Kl_arm64.so
pygsfit/resources/add-button.svg
pygsfit/resources/roi-circ.svg
pygsfit/resources/roi-ellipse.svg
pygsfit/resources/roi-polygon.svg
pygsfit/resources/roi-rect.svg
pygsfit/resources/slice-line.svg
pygsfit/resources/slice-polyline.svg
pygsfit/src_gyrosynchrotron/Arr_DF.cpp
pygsfit/src_gyrosynchrotron/Arr_DF.h
pygsfit/src_gyrosynchrotron/Coulomb.cpp
pygsfit/src_gyrosynchrotron/Coulomb.h
pygsfit/src_gyrosynchrotron/DF.h
pygsfit/src_gyrosynchrotron/ExtMath.cpp
pygsfit/src_gyrosynchrotron/ExtMath.h
pygsfit/src_gyrosynchrotron/FF.cpp
pygsfit/src_gyrosynchrotron/FF.h
pygsfit/src_gyrosynchrotron/GS.cpp
pygsfit/src_gyrosynchrotron/GS.h
pygsfit/src_gyrosynchrotron/IDLinterface.cpp
pygsfit/src_gyrosynchrotron/IDLinterface.h
pygsfit/src_gyrosynchrotron/MWmain.cpp
pygsfit/src_gyrosynchrotron/MWmain.h
pygsfit/src_gyrosynchrotron/Messages.cpp
pygsfit/src_gyrosynchrotron/Messages.h
pygsfit/src_gyrosynchrotron/Plasma.cpp
pygsfit/src_gyrosynchrotron/Plasma.h
pygsfit/src_gyrosynchrotron/PythonInterface.cpp
pygsfit/src_gyrosynchrotron/Std_DF.cpp
pygsfit/src_gyrosynchrotron/Std_DF.h
pygsfit/src_gyrosynchrotron/Zeta.cpp
pygsfit/src_gyrosynchrotron/Zeta.h
pygsfit/src_gyrosynchrotron/dllmain.cpp
pygsfit/src_gyrosynchrotron/getparms.cpp
pygsfit/utils/__init__.py
pygsfit/utils/gstools.py
pygsfit/utils/img_utils.py
pygsfit/utils/ndfits.py
pygsfit/utils/roiutils.py
pygsfit-1.0.15.dist-info/METADATA
pygsfit-1.0.15.dist-info/WHEEL
pygsfit-1.0.15.dist-info/entry_points.txt
pygsfit-1.0.15.dist-info/top_level.txt
pygsfit-1.0.15.dist-info/RECORD
