Metadata-Version: 2.4
Name: pygsfit
Version: 1.0.15
Summary: Python GUI for spectral fitting of radio spectral imaging data
Author: Bin Chen, Sijie Yu, Yuqian Wei, Surajit Mondal
License: MIT
Keywords: astronomy,spectral,fitting,gui,solar,radio
Classifier: Development Status :: 4 - Beta
Classifier: Intended Audience :: Science/Research
Classifier: Topic :: Scientific/Engineering :: Astronomy
Classifier: License :: OSI Approved :: MIT License
Classifier: Programming Language :: Python :: 3
Classifier: Programming Language :: Python :: 3.8
Classifier: Programming Language :: Python :: 3.9
Classifier: Programming Language :: Python :: 3.10
Classifier: Programming Language :: Python :: 3.11
Classifier: Programming Language :: Python :: 3.12
Classifier: Operating System :: OS Independent
Requires-Python: >=3.8
Requires-Dist: astropy
Requires-Dist: corner
Requires-Dist: h5py
Requires-Dist: lmfit
Requires-Dist: matplotlib
Requires-Dist: numpy
Requires-Dist: pyqtgraph
Requires-Dist: PyQt5
Requires-Dist: regions
Requires-Dist: scipy
Requires-Dist: shapely
Requires-Dist: sunpy[all]
Requires-Dist: tqdm
Requires-Dist: emcee>=3.0.0
Requires-Dist: Pandas>=2.2.0
